regxdev/__init__.py
regxdev/regxdev.py
regxdev-1.0.0.dist-info/LICENSE
regxdev-1.0.0.dist-info/METADATA
regxdev-1.0.0.dist-info/WHEEL
regxdev-1.0.0.dist-info/top_level.txt
regxdev-1.0.0.dist-info/RECORD
