Metadata-Version: 2.1
Name: regxdev
Version: 1.0.0
Summary: This package is made especially for developers or web scrapers for saving time while scraping the information.
Home-page: https://github.com/mr-elliot/Regx-Dev/
Author: Sanjay kumar J
Author-email: sanjaykumarj222@gmail.com
License: UNKNOWN
Project-URL: Bug Reports, https://github.com/mr-elliot/Regx-Dev/issues
Project-URL: Source, https://github.com/mr-elliot/Regx-Dev/
Keywords: re,phone-scrape,finding
Platform: UNKNOWN
Classifier: Programming Language :: Python :: 3
Classifier: License :: OSI Approved :: MIT License
Classifier: Operating System :: OS Independent
Requires-Python: >=3.6
